{
  "id": "ch3_lv6",
  "chapter": 3,
  "seed": 30006,
  "objective": {
    "kind": "survive"
  },
  "board": {
    "activeLanes": [
      0,
      2,
      3,
      9,
      10
    ]
  },
  "waves": {
    "entries": [
      {
        "atTick": 120,
        "unitType": "runner",
        "col": 0,
        "count": 2,
        "spacingTicks": 10
      },
      {
        "atTick": 120,
        "unitType": "runner",
        "col": 10,
        "count": 2,
        "spacingTicks": 10
      },
      {
        "atTick": 360,
        "unitType": "infantry",
        "col": 3,
        "count": 2,
        "spacingTicks": 14,
        "crossWaypoints": [
          {
            "atRow": 8,
            "toCol": 9
          }
        ]
      },
      {
        "atTick": 360,
        "unitType": "infantry",
        "col": 2,
        "count": 2,
        "spacingTicks": 14
      },
      {
        "atTick": 480,
        "unitType": "shieldbearer",
        "col": 0,
        "count": 1,
        "spacingTicks": 26
      },
      {
        "atTick": 480,
        "unitType": "runner",
        "col": 9,
        "count": 4,
        "spacingTicks": 8
      },
      {
        "atTick": 660,
        "unitType": "ironclad",
        "col": 2,
        "count": 1,
        "spacingTicks": 38
      },
      {
        "atTick": 660,
        "unitType": "runner",
        "col": 0,
        "count": 4,
        "spacingTicks": 8
      },
      {
        "atTick": 660,
        "unitType": "infantry",
        "col": 10,
        "count": 4,
        "spacingTicks": 13
      },
      {
        "atTick": 900,
        "unitType": "ironclad",
        "col": 3,
        "count": 1,
        "spacingTicks": 36,
        "crossWaypoints": [
          {
            "atRow": 8,
            "toCol": 9
          }
        ]
      },
      {
        "atTick": 900,
        "unitType": "shieldbearer",
        "col": 9,
        "count": 2,
        "spacingTicks": 20
      },
      {
        "atTick": 900,
        "unitType": "runner",
        "col": 0,
        "count": 4,
        "spacingTicks": 8
      },
      {
        "atTick": 1140,
        "unitType": "ironclad",
        "col": 0,
        "count": 1,
        "spacingTicks": 34
      },
      {
        "atTick": 1140,
        "unitType": "ironclad",
        "col": 10,
        "count": 1,
        "spacingTicks": 34
      },
      {
        "atTick": 1140,
        "unitType": "runner",
        "col": 2,
        "count": 5,
        "spacingTicks": 7
      },
      {
        "atTick": 1140,
        "unitType": "runner",
        "col": 9,
        "count": 5,
        "spacingTicks": 7
      },
      {
        "atTick": 1320,
        "unitType": "shieldbearer",
        "col": 3,
        "count": 2,
        "spacingTicks": 20,
        "crossWaypoints": [
          {
            "atRow": 8,
            "toCol": 9
          }
        ]
      },
      {
        "atTick": 1320,
        "unitType": "infantry",
        "col": 2,
        "count": 4,
        "spacingTicks": 12
      },
      {
        "atTick": 1320,
        "unitType": "ironclad",
        "col": 0,
        "count": 1,
        "spacingTicks": 32
      }
    ]
  },
  "rewards": {
    "starThresholds": [
      1,
      50,
      80
    ],
    "materials": {
      "scrap": 11,
      "lead": 6,
      "binding": 1
    }
  },
  "nameKey": "campaign.ch3.lv6.name",
  "briefKey": "campaign.ch3.lv6.brief",
  "startInk": 5,
  "inkRegenMult": 1.04,
  "enemyScale": {
    "hp": 1.105,
    "damage": 1.085
  }
}
